{
    "channel": "scorpion8182",
    "players": {},
    "devs": ["scorpion8182", "paigfx", "mrdeathappears", "BothLine"],
    "nations": [
        {
            "members": [],
            "wallet": 0,
            "name": "water"
        },
        {
            "members": [],
            "wallet": 0,
            "name": "fire"
        },
        {
            "members": [],
            "wallet": 0,
            "name": "air"
        },
        {
            "members": [],
            "wallet": 0,
            "name": "earth"
        }
    ],
    "stock": [
        {
            "amount": -1,
            "slot": "mount",
            "item": {
                "name": "flyingbison",
                "expire": 604800,
                "maxAmount": 1,
                "nation": "air",
                "statRequired": {
                    "level": -1
                },
                "cost": 2000,
                "statInfluence": {}
            }
        },
        {
            "amount": -1,
            "slot": "mount",
            "item": {
                "name": "badgermole",
                "expire": 604800,
                "maxAmount": 1,
                "nation": "earth",
                "statRequired": {
                    "level": -1
                },
                "cost": 2000,
                "statInfluence": {}
            }
        },
        {
            "amount": -1,
            "slot": "mount",
            "item": {
                "name": "dragon",
                "expire": 604800,
                "maxAmount": 1,
                "nation": "fire",
                "statRequired": {
                    "level": -1
                },
                "cost": 2000,
                "statInfluence": {}
            }
        },
        {
            "amount": -1,
            "slot": "mount",
            "item": {
                "name": "polarbeardog",
                "expire": 604800,
                "maxAmount": 1,
                "nation": "water",
                "statRequired": {
                    "level": -1
                },
                "cost": 2000,
                "statInfluence": {}
            }
        },
        {
            "amount": -1,
            "slot": "upkeep",
            "item": {
                "name": "baseupkeep",
                "expire": 604800,
                "maxAmount": -1,
                "nation": "",
                "statRequired": {
                    "level": -1
                },
                "cost": 20,
                "statInfluence": {}
            }
        },
        {
            "amount": -1,
            "slot": "shoe",
            "item": {
                "name": "baseshoe",
                "expire": -1,
                "maxAmount": 1,
                "nation": "",
                "statRequired": {
                    "level": -1
                },
                "cost": 10,
                "statInfluence": {
                    "dexterity": 1
                }
            }
        },
        {
            "amount": -1,
            "slot": "chest",
            "item": {
                "name": "basechest",
                "expire": -1,
                "maxAmount": 1,
                "nation": "",
                "statRequired": {
                    "level": -1
                },
                "cost": 20,
                "statInfluence": {
                    "HP": 1
                }
            }
        },
        {
            "amount": -1,
            "slot": "hat",
            "item": {
                "name": "basehat",
                "expire": -1,
                "maxAmount": 1,
                "nation": "",
                "statRequired": {
                    "level": -1
                },
                "cost": 8,
                "statInfluence": {
                    "intelligence": 1
                }
            }
        },
        {
            "amount": -1,
            "slot": "coat",
            "item": {
                "name": "basecoat",
                "expire": -1,
                "maxAmount": 1,
                "nation": "",
                "statRequired": {
                    "level": -1
                },
                "cost": 10,
                "statInfluence": {
                    "charisma": 1
                }
            }
        },
        {
            "amount": -1,
            "slot": "pants",
            "item": {
                "name": "basepants",
                "expire": -1,
                "maxAmount": 1,
                "nation": "",
                "statRequired": {
                    "level": -1
                },
                "cost": 15,
                "statInfluence": {
                    "toughness": 1
                }
            }
        }
    ]
}
